hotsos/.repo-info
hotsos/__init__.py
hotsos/cli.py
hotsos/client.py
hotsos/core/__init__.py
hotsos/core/analytics.py
hotsos/core/config.py
hotsos/core/exceptions.py
hotsos/core/factory.py
hotsos/core/log.py
hotsos/core/plugintools.py
hotsos/core/root_manager.py
hotsos/core/search.py
hotsos/core/utils.py
hotsos/core/host_helpers/__init__.py
hotsos/core/host_helpers/apparmor.py
hotsos/core/host_helpers/common.py
hotsos/core/host_helpers/config.py
hotsos/core/host_helpers/exceptions.py
hotsos/core/host_helpers/filestat.py
hotsos/core/host_helpers/network.py
hotsos/core/host_helpers/packaging.py
hotsos/core/host_helpers/pebble.py
hotsos/core/host_helpers/ssl.py
hotsos/core/host_helpers/sysctl.py
hotsos/core/host_helpers/systemd.py
hotsos/core/host_helpers/uptime.py
hotsos/core/host_helpers/cli/__init__.py
hotsos/core/host_helpers/cli/catalog.py
hotsos/core/host_helpers/cli/cli.py
hotsos/core/host_helpers/cli/common.py
hotsos/core/host_helpers/cli/commands/__init__.py
hotsos/core/host_helpers/cli/commands/ceph.py
hotsos/core/host_helpers/cli/commands/kubectl.py
hotsos/core/host_helpers/cli/commands/ovn.py
hotsos/core/host_helpers/cli/commands/ovs.py
hotsos/core/issues/__init__.py
hotsos/core/issues/issue_types.py
hotsos/core/issues/utils.py
hotsos/core/plugins/__init__.py
hotsos/core/plugins/kubernetes.py
hotsos/core/plugins/landscape.py
hotsos/core/plugins/maas.py
hotsos/core/plugins/mysql.py
hotsos/core/plugins/pacemaker.py
hotsos/core/plugins/sosreport.py
hotsos/core/plugins/vault.py
hotsos/core/plugins/juju/__init__.py
hotsos/core/plugins/juju/common.py
hotsos/core/plugins/juju/resources.py
hotsos/core/plugins/kernel/__init__.py
hotsos/core/plugins/kernel/common.py
hotsos/core/plugins/kernel/config.py
hotsos/core/plugins/kernel/memory.py
hotsos/core/plugins/kernel/net.py
hotsos/core/plugins/kernel/sysfs.py
hotsos/core/plugins/kernel/kernlog/__init__.py
hotsos/core/plugins/kernel/kernlog/calltrace.py
hotsos/core/plugins/kernel/kernlog/common.py
hotsos-1.20.post61.dist-info/LICENSE
hotsos-1.20.post61.dist-info/METADATA
hotsos-1.20.post61.dist-info/WHEEL
hotsos-1.20.post61.dist-info/entry_points.txt
hotsos-1.20.post61.dist-info/top_level.txt
hotsos-1.20.post61.dist-info/RECORD
