Metadata-Version: 2.1
Name: hotsos
Version: 1.20.post61
Summary: Software analysis toolkit. Define checks in high-level language and leverage library to perform analysis of common Cloud applications.
Requires-Python: >=3.8
License-File: LICENSE
Requires-Dist: click
Requires-Dist: cryptography
Requires-Dist: distro
Requires-Dist: fasteners
Requires-Dist: jinja2
Requires-Dist: progress
Requires-Dist: propertree>=2.1
Requires-Dist: pyyaml
Requires-Dist: searchkit>=0.4.3.post6
Requires-Dist: simplejson
Requires-Dist: sphinx>=4.3.2
Requires-Dist: python-dateutil
Requires-Dist: pytz
Requires-Dist: importlib-metadata; python_version >= "3.8"
